README.txt
setup.py
collective/__init__.py
collective.portlet.postit.egg-info/PKG-INFO
collective.portlet.postit.egg-info/SOURCES.txt
collective.portlet.postit.egg-info/dependency_links.txt
collective.portlet.postit.egg-info/entry_points.txt
collective.portlet.postit.egg-info/namespace_packages.txt
collective.portlet.postit.egg-info/not-zip-safe
collective.portlet.postit.egg-info/requires.txt
collective.portlet.postit.egg-info/top_level.txt
collective/portlet/__init__.py
collective/portlet/postit/__init__.py
collective/portlet/postit/configure.zcml
collective/portlet/postit/fetcher.py
collective/portlet/postit/interfaces.py
collective/portlet/postit/portlet.css
collective/portlet/postit/portlet.pt
collective/portlet/postit/portlet.py
collective/portlet/postit/postit.py
collective/portlet/postit/postiticon.gif
collective/portlet/postit/profile/catalog.xml
collective/portlet/postit/profile/cssregistry.xml
collective/portlet/postit/profile/factorytool.xml
collective/portlet/postit/profile/portlets.xml
collective/portlet/postit/profile/types.xml
collective/portlet/postit/profile/types/PostIt.xml
