Metadata-Version: 1.0
Name: collective.portlet.postit
Version: 1.0-beta1
Summary: Post-It portlet and content type for Plone 3.
Home-page: http://svn.plone.org/svn/collective/collective.portlet.postit
Author: Jens Klein
Author-email: jens@bluedynamics.com
License: GPL
Platform: UNKNOWN
Classifier: Framework :: Plone
Classifier: Framework :: Zope2
Classifier: Framework :: Zope3
Classifier: Programming Language :: Python
Classifier: Topic :: Software Development :: Libraries :: Python Modules
